cttg/__init__.py
chefs_ttg-1.1.1.dist-info/LICENCE.txt
chefs_ttg-1.1.1.dist-info/METADATA
chefs_ttg-1.1.1.dist-info/WHEEL
chefs_ttg-1.1.1.dist-info/top_level.txt
chefs_ttg-1.1.1.dist-info/RECORD
